tsopt/__init__.py
tsopt/constants.py
tsopt/container.py
tsopt/edges.py
tsopt/globals.py
tsopt/model.py
tsopt/nodes.py
tsopt/values.py
tsopt/solved/__init__.py
tsopt/solved/plots.py
tsopt/solved/solution.py
tsopt/solved/solved_model.py
tsopt/types/__init__.py
tsopt/types/data_types.py
tsopt/types/list_data.py
tsopt/util/__init__.py
tsopt/util/exceptions.py
tsopt/util/pandas_added_methods.py
tsopt/util/plot_util.py
tsopt/util/text_util.py
tsopt/util/vector_util.py
tsopt/validation/validate.py
tsopt-0.0.37.dist-info/METADATA
tsopt-0.0.37.dist-info/WHEEL
tsopt-0.0.37.dist-info/licenses/LICENSE
tsopt-0.0.37.dist-info/RECORD
