Metadata-Version: 2.1
Name: tsopt
Version: 0.0.37
Summary: Easily solve any multi-stage transshipment cost minimization optimization problem
Project-URL: Homepage, https://github.com/ryayoung/tsopt
Project-URL: Web App, https://tsopt.net
Author-email: Ryan Young <dev@ryayoung.com>
Maintainer-email: Ryan Young <dev@ryayoung.com>
License: Copyright 2022 Ryan Young
License-File: LICENSE
Keywords: inventory,linear programming,network flow,optimization,supply chain
Classifier: License :: OSI Approved :: MIT License
Classifier: Operating System :: OS Independent
Classifier: Programming Language :: Python :: 3.9
Requires-Python: >=3.9
Requires-Dist: matplotlib
Requires-Dist: pandas
Requires-Dist: plotly
Requires-Dist: pulp
Requires-Dist: seaborn
